searchnarwhal/__init__.py
searchnarwhal/browser.py
searchnarwhal/download.py
searchnarwhal/localres.py
searchnarwhal/web.py
searchnarwhal-0.1.0.dist-info/LICENSE
searchnarwhal-0.1.0.dist-info/METADATA
searchnarwhal-0.1.0.dist-info/WHEEL
searchnarwhal-0.1.0.dist-info/top_level.txt
searchnarwhal-0.1.0.dist-info/RECORD
